README.txt
setup.py
bin/simplify.py
visvalingam/__init__.py
visvalingam/visvalingam.py
visvalingam.egg-info/PKG-INFO
visvalingam.egg-info/SOURCES.txt
visvalingam.egg-info/dependency_links.txt
visvalingam.egg-info/top_level.txt
visvalingam/classes/__init__.py
visvalingam/classes/checkArguments.py