Metadata-Version: 1.1
Name: visvalingam
Version: 0.3.0
Summary: Simple implementation of the Visvalingam-Wyatt algorithm
Home-page: http://milkbread.github.io/Visvalingam-Wyatt
Author: Mathieu (matael) Gaborit
Author-email: mathieu@matael.org
License: MIT
Platform: UNKNOWN
Classifier: Programming Language :: Python
Classifier: Intended Audience :: Developers
